conform/__init__.py
conform/cli.py
conform/formatter.py
conform/mapping.py
conform/models.py
conform/nodes.py
conform/parser.py
conform-0.1.0.dist-info/LICENSE
conform-0.1.0.dist-info/METADATA
conform-0.1.0.dist-info/WHEEL
conform-0.1.0.dist-info/entry_points.txt
conform-0.1.0.dist-info/top_level.txt
conform-0.1.0.dist-info/RECORD
